aws/__init__.py
aws/ecs_bash.py
aws/resources/__init__.py
aws/resources/db-connect.sh
aws/resources/db-decrypt.js
f_tools-4.3.9.dist-info/METADATA
f_tools-4.3.9.dist-info/WHEEL
f_tools-4.3.9.dist-info/entry_points.txt
f_tools-4.3.9.dist-info/top_level.txt
f_tools-4.3.9.dist-info/RECORD
