Metadata-Version: 2.2
Name: f-tools
Version: 4.3.9
Summary: AWS tools including ECS bash execution
Author-email: Filipe Ferreira <code@filipeandre.com>
Project-URL: Homepage, https://github.com/filipeandre/f-tools
Requires-Dist: boto3
Requires-Dist: inquirer
